st_bidirectional_text/__init__.py
st_bidirectional_text/frontend/button.html
st_bidirectional_text/frontend/index.html
st_bidirectional_text/frontend/main copy.js
st_bidirectional_text/frontend/main.js
st_bidirectional_text/frontend/streamlit-component-lib.js
st_bidirectional_text/frontend/style.css
bidirectional_text-0.1.0.dist-info/LICENSE
bidirectional_text-0.1.0.dist-info/METADATA
bidirectional_text-0.1.0.dist-info/WHEEL
bidirectional_text-0.1.0.dist-info/top_level.txt
bidirectional_text-0.1.0.dist-info/RECORD
