Metadata-Version: 2.1
Name: bidirectional-text
Version: 0.1.0
Summary: A streamlit component that allows you to get input from a textbox after every key press
Author: hakan emekci
Author-email: hakanemekci@gmail.com
Requires-Python: >=3.7
License-File: LICENSE
Requires-Dist: streamlit >=1.2
Requires-Dist: jinja2
